[
  {
    "key": "0-teller",
    "original": "궁금한 동료",
    "context": "EN :\nCurious Coworker\nJP :\n気になる様子の同僚"
  },
  {
    "key": "0-title",
    "original": "세븐 협회 6과",
    "context": "EN :\nSeven Section 6\nJP :\nセブン協会 6課"
  },
  {
    "key": "0-content",
    "original": "…너는 대체 왜 세븐에 있는 거야?",
    "context": "EN :\n…Why do you even bother staying in the Seven?\nJP :\n…君は一体何でセブンにいるんだ？"
  },
  {
    "key": "1-model",
    "original": "료슈",
    "translation": "良秀",
    "context": "EN :\nRyōshū\nJP :\n良秀"
  },
  {
    "key": "1-title",
    "original": "세븐 협회 6과",
    "context": "EN :\nSeven Section 6\nJP :\nセブン協会 6課"
  },
  {
    "key": "1-content",
    "original": "별, 없.",
    "context": "EN :\nN. M.\nJP :\nべつ、ない。"
  },
  {
    "key": "2-content",
    "original": "아이는 상대방의 질문에는 항상 차갑게 대꾸했어. ",
    "context": "EN :\nThe child was always harsh to others’ questions.\nJP :\n子供は相手の質問にはいつも冷たく答えた。"
  },
  {
    "key": "3-content",
    "original": "그런 행동 역시 별 의미는 없었지만, 세븐 협회는 오히려 그런 아이의 특징에 초점을 두었지.",
    "context": "EN :\nWhile her snappish replies weren’t a result of meticulous calculation, the Seven Association nevertheless took an interest in that trait of hers.\nJP :\nそういった行動に特段意味はなかったけど、\nセブン協会はむしろそういう子供の特徴に焦点を置いたんだ。"
  },
  {
    "key": "4-content",
    "original": "‘정보의 비대칭성’.",
    "context": "EN :\n“Information Dissymmetry.”\nJP :\n「情報の非対称性」"
  },
  {
    "key": "5-content",
    "original": "세븐이 정보를 모으지만, 상대에게는 세븐의 정보를 주지 않는 것이 그들의 규칙이었어.",
    "context": "EN :\nAlthough the Seven Association specializes in gathering intelligence, it’s never easily shared its knowledge with others on principle.\nJP :\nセブンは情報を集めるが、\n相手にはセブンの情報を与えないのが彼らのルールだった。"
  },
  {
    "key": "6-content",
    "original": "그런 부분에서, 아이는 대부분의 정보를 남에게 넘기는 걸 꺼려했지. 입이 무겁다고 해야 할까?",
    "context": "EN :\nIn that sense, the child could be seen as someone discreet about her info. A woman of few words, if you will?\nJP :\nそういった点で、子供は大体の情報を他人に渡すのを嫌がった。\n口が堅いというべきかな？"
  },
  {
    "key": "7-content",
    "original": "물론, 의도해서 하는 행동은 아니었지만 말이야.",
    "context": "EN :\nOf course, that wasn’t necessarily her intention.\nJP :\nもちろん、意図的な行動じゃなかったけど。"
  },
  {
    "key": "8-content",
    "original": "그저 검을 놀릴 곳이 아이에게 필요했을 뿐일 가능성이, 더 높을 것 같네.",
    "context": "EN :\nIt’s far more likely that the child just needed an excuse to swing her sword.\nJP :\nただ剣を振り回す場所が子供に必要だっただけ、\nという可能性の方が高いかもしれないね。"
  },
  {
    "key": "9-model",
    "original": "료슈",
    "translation": "良秀",
    "context": "EN :\nRyōshū\nJP :\n良秀"
  },
  {
    "key": "9-title",
    "original": "세븐 협회 6과",
    "context": "EN :\nSeven Section 6\nJP :\nセブン協会 6課"
  },
  {
    "key": "9-content",
    "original": "…훗, 잘 보라고.",
    "context": "EN :\n…Hmph, watch and learn.\nJP :\n…ふっ、よく見てろ。"
  },
  {
    "key": "10-content",
    "original": "아이는 검을 특이한 자세로 치켜들더니, 순식간에 검을 놀려댔어.",
    "context": "EN :\nThe child lifted her weapon with an unorthodox posture and got to work.\nJP :\n子供は剣を変わった姿勢で振りかざし、瞬時に操ってみせた。"
  },
  {
    "key": "11-content",
    "original": "검이 목표에 닿을 때마다 그것은 벗겨지고, 잘려나가고, 조각나고, 흩어져서는…",
    "context": "EN :\nEach spot targeted and touched by her sword was peeled, cut, sliced, strewn…\nJP :\n剣が目標に達するたびにそれは剥がれ、切り取られ、砕け、散らばり…。"
  },
  {
    "key": "12-model",
    "original": "료슈",
    "translation": "良秀",
    "context": "EN :\nRyōshū\nJP :\n良秀"
  },
  {
    "key": "12-title",
    "original": "세븐 협회 6과",
    "context": "EN :\nSeven Section 6\nJP :\nセブン協会 6課"
  },
  {
    "key": "12-content",
    "original": "검만예극…",
    "context": "EN :\nPACTS…\nJP :\n剣創芸極…。"
  },
  {
    "key": "13-content",
    "original": "검으로 만들어내는 예술의 극치.",
    "context": "EN :\nPeak art created through swordsmanship.\nJP :\n剣で創り出す芸術の極致。"
  },
  {
    "key": "14-content",
    "original": "그 말 그대로, 눈 앞의 그것은 사람과는 너무나 다른 형태의 살 덩어리로 변해 버렸어.",
    "context": "EN :\nShe left a lump of flesh that could no longer be recognized as a human in her wake.\nJP :\n文字通り、目の前のそれは人間とはあまりにも\nかけ離れた形の肉の塊に変わってしまったんだ。"
  }
]